LGSamsungAppletest/test1.py
LGSamsungAppletest/test2.py
LGSamsungAppletest-0.0.0.2.dist-info/METADATA
LGSamsungAppletest-0.0.0.2.dist-info/WHEEL
LGSamsungAppletest-0.0.0.2.dist-info/top_level.txt
LGSamsungAppletest-0.0.0.2.dist-info/RECORD
