Metadata-Version: 2.1
Name: LGSamsungAppletest
Version: 0.0.0.2
Summary: My First Test Package
Home-page: https://lingua.blog.me/…
Author: eunseongLim
Author-email: les1503@naver.com
License: MIT
Requires-Python: >=3
